setup.py
codecheckers/__init__.py
codecheckers/flakes.py
codecheckers/pep.py
codecheckers/plugin.py
pytest_codecheckers.egg-info/PKG-INFO
pytest_codecheckers.egg-info/SOURCES.txt
pytest_codecheckers.egg-info/dependency_links.txt
pytest_codecheckers.egg-info/entry_points.txt
pytest_codecheckers.egg-info/requires.txt
pytest_codecheckers.egg-info/top_level.txt