Metadata-Version: 1.0
Name: pytest-codecheckers
Version: 0.2
Summary: pytest plugin to add source code sanity checks (pep8 and friends)
Home-page: UNKNOWN
Author: Ronny Pfannschmidt
Author-email: Ronny.Pfannschmidt@gmx.de
License: UNKNOWN
Platform: UNKNOWN
